multi_proto_agent-0.1.2.dist-info/licenses/LICENSE
utils/ReportInform.py
utils/__init__.py
utils/assert_util.py
utils/clean_up_util.py
utils/config_util.py
utils/logger_config.py
utils/player.py
utils/random_util.py
utils/report_util.py
utils/run_java_util.py
utils/tcp_util.py
utils/trace_id_util.py
utils/translator.py
utils/websocket_util.py
multi_proto_agent-0.1.2.dist-info/METADATA
multi_proto_agent-0.1.2.dist-info/WHEEL
multi_proto_agent-0.1.2.dist-info/top_level.txt
multi_proto_agent-0.1.2.dist-info/RECORD
