Metadata-Version: 2.4
Name: multi-proto-agent
Version: 0.1.2
Summary: 旨在简化基于多种协议的消息通信,内置了对JSON和Protobuf的序列化、反序列化支持，并设计为线程安全，让你可以轻松创建和管理成百上千个并发通信代理。
Home-page: https://gitee.com/flinttina/multi-proto-agent
Author: Shi Feng
Author-email: 330550850@qq.com
Classifier: Programming Language :: Python :: 3
Classifier: License :: OSI Approved :: MIT License
Classifier: Operating System :: OS Independent
Requires-Python: >=3.8
License-File: LICENSE
Requires-Dist: protobuf>=5.28.3
Requires-Dist: PyYAML>=6.0.2
Requires-Dist: jsonpath-ng>=1.7.0
Requires-Dist: websocket-client>=1.9.0
Requires-Dist: paramiko>=4.0.0
Requires-Dist: requests>=2.32.3
Requires-Dist: gevent>=25.9.1
Requires-Dist: certifi>=2024.7.4
Requires-Dist: charset-normalizer>=3.3.2
Requires-Dist: idna>=3.7
Requires-Dist: urllib3>=2.2.2
Requires-Dist: bcrypt>=5.0.0
Requires-Dist: cryptography>=46.0.1
Requires-Dist: PyNaCl>=1.6.0
Requires-Dist: cffi>=2.0.0
Requires-Dist: pycparser>=2.23
Requires-Dist: greenlet>=3.2.4
Requires-Dist: zope.event>=6.0
Requires-Dist: zope.interface>=8.0
Requires-Dist: six>=1.16.0
Requires-Dist: ply>=3.11
Requires-Dist: decorator>=5.1.1
Requires-Dist: pytest>=8.3.3
Requires-Dist: pytest-html>=4.1.1
Requires-Dist: pytest-metadata>=3.1.1
Requires-Dist: pytest-order>=1.3.0
Requires-Dist: pytest-ordering>=0.6
Requires-Dist: pytest-repeat>=0.9.4
Requires-Dist: pytest-timeout>=2.3.1
Requires-Dist: pytest-xdist>=3.6.1
Requires-Dist: attrs>=24.2.0
Requires-Dist: iniconfig>=2.0.0
Requires-Dist: pluggy>=1.5.0
Requires-Dist: py>=1.11.0
Requires-Dist: packaging>=25.0
Requires-Dist: colorama>=0.4.6
Requires-Dist: allure-pytest>=2.13.5
Requires-Dist: allure-python-commons>=2.13.5
Requires-Dist: lxml>=5.3.0
Requires-Dist: execnet>=2.1.1
Requires-Dist: python-dateutil>=2.9.0.post0
Requires-Dist: pytz>=2024.2
Requires-Dist: tzdata>=2024.2
Dynamic: author
Dynamic: author-email
Dynamic: classifier
Dynamic: description
Dynamic: description-content-type
Dynamic: home-page
Dynamic: license-file
Dynamic: requires-dist
Dynamic: requires-python
Dynamic: summary
